fuzzytree/__init__.py
fuzzytree/_classes.py
fuzzytree/_criterion.py
fuzzytree/_fuzzy_decision_rule.py
fuzzytree/_fuzzy_tree.py
fuzzytree/_splitter.py
fuzzytree/_utils.py
fuzzytree/_version.py
fuzzytree/tests/__init__.py
fuzzytree/tests/test_classifier.py
fuzzytree/tests/test_common.py
fuzzytree-0.2.0.dist-info/LICENSE
fuzzytree-0.2.0.dist-info/METADATA
fuzzytree-0.2.0.dist-info/WHEEL
fuzzytree-0.2.0.dist-info/top_level.txt
fuzzytree-0.2.0.dist-info/RECORD
